ascii_designer/__init__.py
ascii_designer/__version__.py
ascii_designer/ascii_slice.py
ascii_designer/asymmetric_descriptor.py
ascii_designer/autoframe.py
ascii_designer/event.py
ascii_designer/i18n.py
ascii_designer/list_model.py
ascii_designer/tk_generic_var.py
ascii_designer/tk_treeedit.py
ascii_designer/tk_treeview.py
ascii_designer/toolkit.py
ascii_designer/toolkit_qt.py
ascii_designer/toolkit_tk.py
ascii_designer-2.0.0.dist-info/licenses/LICENSE
ascii_designer-2.0.0.dist-info/METADATA
ascii_designer-2.0.0.dist-info/WHEEL
ascii_designer-2.0.0.dist-info/top_level.txt
ascii_designer-2.0.0.dist-info/RECORD
