Metadata-Version: 2.4
Name: ascii_designer
Version: 2.0.0
Summary: Builds dialogs from ASCII art definition.
Author-email: Johannes Loehnert <loehnert.kde@gmx.de>
License: Copyright 2018 J. Löhnert
Project-URL: Homepage, http://github.com/loehnertj/ascii_designer
Project-URL: Repository, http://github.com/loehnertj/ascii_designer
Project-URL: Documentation, https://ascii-designer.readthedocs.io/
Project-URL: Issues, http://github.com/loehnertj/ascii_designer/issues
Classifier: Development Status :: 4 - Beta
Classifier: License :: OSI Approved :: MIT License
Classifier: Programming Language :: Python :: 3
Classifier: Topic :: Software Development :: User Interfaces
Requires-Python: >3.7
License-File: LICENSE
Provides-Extra: qtsupport
Requires-Dist: qtpy; extra == "qtsupport"
Dynamic: license-file
